oxc_py-0.1.3.dist-info/METADATA
oxc_py-0.1.3.dist-info/WHEEL
oxc_py/__init__.py
oxc_py/oxc_py.cpython-38-i386-linux-gnu.so
oxc_py-0.1.3.dist-info/RECORD
