Metadata-Version: 2.4
Name: oxc-py
Version: 0.1.3
Classifier: Programming Language :: Rust
Classifier: Programming Language :: Python :: Implementation :: CPython
Classifier: Programming Language :: Python :: Implementation :: PyPy
Requires-Dist: pytest>=6.2.4 ; extra == 'dev'
Requires-Dist: maturin>=1.9.6 ; extra == 'dev'
Provides-Extra: dev
Requires-Python: >=3.8
